pyforms_generic_editor/__init__.py
pyforms_generic_editor/__main__.py
pyforms_generic_editor/settings.py
pyforms_generic_editor/editor/__init__.py
pyforms_generic_editor/editor/base_editor.py
pyforms_generic_editor/editor/generic_file_editor.py
pyforms_generic_editor/editor/safe_mode_editor.py
pyforms_generic_editor/models/__init__.py
pyforms_generic_editor/models/project/__init__.py
pyforms_generic_editor/models/project/generic_project.py
pyforms_generic_editor/models/projects/__init__.py
pyforms_generic_editor/models/projects/projects_dockwindow.py
pyforms_generic_editor/models/projects/projects_treenode.py
pyforms_generic_editor/models/projects/projects_window.py
pyforms_generic_editor/plugins/__init__.py
pyforms_generic_editor/plugins/loader.py
pyforms_generic_editor/resources/__init__.py
pyforms_generic_editor/resources/__pycache__/__init__.cpython-36.pyc
pyforms_generic_editor/resources/icons/add.png
pyforms_generic_editor/resources/icons/busy.png
pyforms_generic_editor/resources/icons/cf-original.png
pyforms_generic_editor/resources/icons/close.png
pyforms_generic_editor/resources/icons/exit.png
pyforms_generic_editor/resources/icons/new.png
pyforms_generic_editor/resources/icons/open.png
pyforms_generic_editor/resources/icons/play.png
pyforms_generic_editor/resources/icons/project.png
pyforms_generic_editor/resources/icons/remove.png
pyforms_generic_editor/resources/icons/save.png
pyforms_generic_editor/resources/icons/settings.png
pyforms_generic_editor/resources/themes/d-theme-blue/checkbox.png
pyforms_generic_editor/resources/themes/d-theme-blue/d-theme-blue.qss
pyforms_generic_editor/resources/themes/d-theme-blue/down_arrow.png
pyforms_generic_editor/resources/themes/d-theme-blue/down_arrow_disabled.png
pyforms_generic_editor/resources/themes/d-theme-blue/left_arrow.png
pyforms_generic_editor/resources/themes/d-theme-blue/left_arrow_disabled.png
pyforms_generic_editor/resources/themes/d-theme-blue/move_toolbar_hor.png
pyforms_generic_editor-1.5.1.dist-info/LICENSE
pyforms_generic_editor-1.5.1.dist-info/METADATA
pyforms_generic_editor-1.5.1.dist-info/WHEEL
pyforms_generic_editor-1.5.1.dist-info/entry_points.txt
pyforms_generic_editor-1.5.1.dist-info/top_level.txt
pyforms_generic_editor-1.5.1.dist-info/RECORD
