Metadata-Version: 2.1
Name: pyforms-generic-editor
Version: 1.5.1
Summary: pyforms_generic_editor
Home-page: https://bitbucket.org/fchampalimaud/pyforms-generic-editor
Author: Ricardo Ribeiro & Carlos Mão de Ferro
Author-email: ricardojvr@gmail.com, cajomferro@gmail.com
License: Copyright (C) 2007 Free Software Foundation, Inc. <http://fsf.org/>
Platform: UNKNOWN
